cly_why/__init__.py
cly_why/main.py
cly_why-0.3.12.dist-info/LICENSE
cly_why-0.3.12.dist-info/METADATA
cly_why-0.3.12.dist-info/WHEEL
cly_why-0.3.12.dist-info/RECORD
