Metadata-Version: 2.1
Name: cly-why
Version: 0.3.12
Summary: A super simple functional cli helper lib
Author: 00il
Requires-Python: >=3.10,<4.0
Classifier: Programming Language :: Python :: 3
Classifier: Programming Language :: Python :: 3.10
Classifier: Programming Language :: Python :: 3.11
